farbfeld/__init__.py
farbfeld/decode.py
farbfeld/encode.py
py_farbfeld-1.1.post2.dist-info/LICENSE
py_farbfeld-1.1.post2.dist-info/METADATA
py_farbfeld-1.1.post2.dist-info/WHEEL
py_farbfeld-1.1.post2.dist-info/top_level.txt
py_farbfeld-1.1.post2.dist-info/RECORD
