Metadata-Version: 2.1
Name: py-farbfeld
Version: 1.1.post2
Summary: Implementation of the Suckelss Farbfeld image format in pure Python
Home-page: https://github.com/tryamid/farbfeld
Author: Shantanu Biswas
Author-email: bsantanu381@gmail.com
License: WTFPL
Platform: UNKNOWN
Requires-Python: >=3.5
